LICENSE
README.md
setup.py
lzstr/BitString.py
lzstr/Exceptions.py
lzstr/LZString.py
lzstr/__init__.py
lzstr.egg-info/PKG-INFO
lzstr.egg-info/SOURCES.txt
lzstr.egg-info/dependency_links.txt
lzstr.egg-info/top_level.txt
lzstr/tests/BitStringTests.py
lzstr/tests/LZStringTests.py
lzstr/tests/__init__.py